keycloak_django/__init__.py
keycloak_django/admin.py
keycloak_django/api/__init__.py
keycloak_django/api/apps.py
keycloak_django/api/urls.py
keycloak_django/api/viewsets.py
keycloak_django/apps.py
keycloak_django/authentication.py
keycloak_django/groups_permissions.py
keycloak_django/keycloak.py
keycloak_django/middleware.py
keycloak_django/migrations/0001_initial.py
keycloak_django/migrations/__init__.py
keycloak_django/models.py
keycloak_django/security.py
keycloak_django/services/__init__.py
keycloak_django/services/client_repository.py
keycloak_django/services/permission_repository.py
keycloak_django/services/realm_repository.py
keycloak_django/services/role_repository.py
keycloak_django/services/user_repository.py
keycloak_django/tools.py
keycloak_django-1.1.21.dist-info/LICENSE
keycloak_django-1.1.21.dist-info/METADATA
keycloak_django-1.1.21.dist-info/WHEEL
keycloak_django-1.1.21.dist-info/RECORD
